COPYING.txt
setup.py
guesslanguage/Blocks.txt
guesslanguage/__init__.py
guesslanguage/blocks.py
guesslanguage/core.py
guesslanguage/langdetect.py
guesslanguage.egg-info/PKG-INFO
guesslanguage.egg-info/SOURCES.txt
guesslanguage.egg-info/dependency_links.txt
guesslanguage.egg-info/not-zip-safe
guesslanguage.egg-info/requires.txt
guesslanguage.egg-info/top_level.txt
guesslanguage/trigrams/af_ZA
guesslanguage/trigrams/ar
guesslanguage/trigrams/az
guesslanguage/trigrams/bg
guesslanguage/trigrams/ca
guesslanguage/trigrams/ceb
guesslanguage/trigrams/cs
guesslanguage/trigrams/cy
guesslanguage/trigrams/da
guesslanguage/trigrams/de_DE
guesslanguage/trigrams/en_US
guesslanguage/trigrams/es
guesslanguage/trigrams/et
guesslanguage/trigrams/eu
guesslanguage/trigrams/fa
guesslanguage/trigrams/fi
guesslanguage/trigrams/fr
guesslanguage/trigrams/ha
guesslanguage/trigrams/haw
guesslanguage/trigrams/hi_IN
guesslanguage/trigrams/hr_HR
guesslanguage/trigrams/hu_HU
guesslanguage/trigrams/id
guesslanguage/trigrams/is
guesslanguage/trigrams/it_IT
guesslanguage/trigrams/kk
guesslanguage/trigrams/ky
guesslanguage/trigrams/la
guesslanguage/trigrams/lt
guesslanguage/trigrams/lv
guesslanguage/trigrams/mk
guesslanguage/trigrams/mn
guesslanguage/trigrams/nb
guesslanguage/trigrams/ne
guesslanguage/trigrams/nl
guesslanguage/trigrams/nr
guesslanguage/trigrams/nso
guesslanguage/trigrams/pl
guesslanguage/trigrams/ps
guesslanguage/trigrams/pt
guesslanguage/trigrams/pt_BR
guesslanguage/trigrams/pt_PT
guesslanguage/trigrams/ro
guesslanguage/trigrams/ru
guesslanguage/trigrams/sk
guesslanguage/trigrams/sl
guesslanguage/trigrams/so
guesslanguage/trigrams/sq
guesslanguage/trigrams/sr
guesslanguage/trigrams/ss
guesslanguage/trigrams/st
guesslanguage/trigrams/sv
guesslanguage/trigrams/sw
guesslanguage/trigrams/tl
guesslanguage/trigrams/tlh
guesslanguage/trigrams/tn
guesslanguage/trigrams/tr
guesslanguage/trigrams/ts
guesslanguage/trigrams/uk
guesslanguage/trigrams/ur
guesslanguage/trigrams/uz
guesslanguage/trigrams/ve
guesslanguage/trigrams/xh
guesslanguage/trigrams/zu_ZA
tests/blocks_test.py