Metadata-Version: 1.0
Name: guesslanguage
Version: 0.1
Summary: Language Guessing library
Home-page: http://silpa.org.in/Guess_Language
Author: Santhosh Thottingal
Author-email: santhosh.thottingal@gmail.com
License: LGPL-3.0
Platform: UNKNOWN
